drill4snap/__init__.py
drill4snap/cli.py
drill4snap/devices.py
drill4snap/drill_pict.png
drill4snap/jobs.py
drill4snap/parser.py
drill4snap/templates.py
drill4snap/writer.py
drill4snap-0.3.0.dist-info/LICENSE
drill4snap-0.3.0.dist-info/METADATA
drill4snap-0.3.0.dist-info/WHEEL
drill4snap-0.3.0.dist-info/entry_points.txt
drill4snap-0.3.0.dist-info/RECORD
