Metadata-Version: 2.1
Name: drill4snap
Version: 0.3.0
Summary: Convert Excellion drill files (such as those produced by KiCad) into G-Code for SnapMaker CNC usage
Home-page: https://github.com/mjleehh/drill4snap
License: LGPL
Author: Michael Jonathan Lee
Requires-Python: >=3.10,<4.0
Classifier: License :: Other/Proprietary License
Classifier: Programming Language :: Python :: 3
Classifier: Programming Language :: Python :: 3.10
Classifier: Programming Language :: Python :: 3.11
Requires-Dist: Pillow (>=9.5.0,<10.0.0)
Requires-Dist: numpy (>=1.24.2,<2.0.0)
Requires-Dist: typer (>=0.7.0,<0.8.0)
